amazon_orders-4.0.18.dist-info/licenses/LICENSE
amazonorders/__init__.py
amazonorders/banner.txt
amazonorders/cli.py
amazonorders/conf.py
amazonorders/constants.py
amazonorders/exception.py
amazonorders/forms.py
amazonorders/orders.py
amazonorders/selectors.py
amazonorders/session.py
amazonorders/transactions.py
amazonorders/util.py
amazonorders/entity/__init__.py
amazonorders/entity/item.py
amazonorders/entity/order.py
amazonorders/entity/parsable.py
amazonorders/entity/recipient.py
amazonorders/entity/seller.py
amazonorders/entity/shipment.py
amazonorders/entity/transaction.py
amazon_orders-4.0.18.dist-info/METADATA
amazon_orders-4.0.18.dist-info/WHEEL
amazon_orders-4.0.18.dist-info/entry_points.txt
amazon_orders-4.0.18.dist-info/top_level.txt
amazon_orders-4.0.18.dist-info/RECORD
