Metadata-Version: 2.4
Name: amazon-orders
Version: 4.0.18
Summary: A Python libray (and CLI) for Amazon order history
Author-email: Alex Laird <contact@alexlaird.com>
Maintainer-email: Alex Laird <contact@alexlaird.com>
License-Expression: MIT
Project-URL: Changelog, https://github.com/alexdlaird/amazon-orders/blob/main/CHANGELOG.md
Project-URL: Documentation, https://amazon-orders.readthedocs.io
Project-URL: Sponsor, https://github.com/sponsors/alexdlaird
Project-URL: Source Code, https://github.com/alexdlaird/amazon-orders
Classifier: Development Status :: 5 - Production/Stable
Classifier: Environment :: Console
Classifier: Environment :: Web Environment
Classifier: Intended Audience :: Developers
Classifier: Operating System :: OS Independent
Classifier: Programming Language :: Python :: 3
Classifier: Programming Language :: Python :: 3.9
Classifier: Programming Language :: Python :: 3.10
Classifier: Programming Language :: Python :: 3.11
Classifier: Programming Language :: Python :: 3.12
Classifier: Topic :: Software Development :: Libraries :: Python Modules
Requires-Python: >=3.9
License-File: LICENSE
Requires-Dist: click>=7.1
Requires-Dist: requests>=2.23
Requires-Dist: amazoncaptcha>=0.4
Requires-Dist: beautifulsoup4>=4.12
Requires-Dist: PyYAML>=5.1
Requires-Dist: python-dateutil>=2.8
Requires-Dist: pyotp>=2.9
Provides-Extra: dev
Requires-Dist: pytest; extra == "dev"
Requires-Dist: coverage[toml]; extra == "dev"
Requires-Dist: flake8; extra == "dev"
Requires-Dist: flake8-pyproject; extra == "dev"
Requires-Dist: pep8-naming; extra == "dev"
Requires-Dist: responses; extra == "dev"
Requires-Dist: lxml; extra == "dev"
Provides-Extra: integration
Requires-Dist: pytest-rerunfailures; extra == "integration"
Requires-Dist: parameterized; extra == "integration"
Provides-Extra: docs
Requires-Dist: Sphinx; extra == "docs"
Requires-Dist: sphinx-notfound-page; extra == "docs"
Requires-Dist: sphinx_autodoc_typehints; extra == "docs"
Requires-Dist: mypy; extra == "docs"
Requires-Dist: types-requests; extra == "docs"
Requires-Dist: types-beautifulsoup4; extra == "docs"
Requires-Dist: types-Pillow; extra == "docs"
Requires-Dist: types-PyYAML; extra == "docs"
Requires-Dist: types-python-dateutil; extra == "docs"
Dynamic: license-file
